geoip.py
python_geoip_yplan-1.2.dist-info/DESCRIPTION.rst
python_geoip_yplan-1.2.dist-info/METADATA
python_geoip_yplan-1.2.dist-info/RECORD
python_geoip_yplan-1.2.dist-info/WHEEL
python_geoip_yplan-1.2.dist-info/metadata.json
python_geoip_yplan-1.2.dist-info/top_level.txt
