Metadata-Version: 2.0
Name: python-geoip-yplan
Version: 1.2
Summary: Provides GeoIP functionality for Python.
Home-page: https://github.com/yplan/python-geoip
Author: Thomas Grainger
Author-email: python-geoip-yplan@graingert.co.uk
License: UNKNOWN
Platform: UNKNOWN
Classifier: Programming Language :: Python
Classifier: Programming Language :: Python :: 2
Classifier: Programming Language :: Python :: 2.6
Classifier: Programming Language :: Python :: 2.7
Classifier: Programming Language :: Python :: 3
Classifier: Programming Language :: Python :: 3.3
Classifier: Programming Language :: Python :: 3.4
Classifier: License :: OSI Approved :: BSD License
